django_cloud_storage/__init__.py
django_cloud_storage/api.py
django_cloud_storage/storage.py
django_cloud_storage-1.0.5.dist-info/LICENSE
django_cloud_storage-1.0.5.dist-info/METADATA
django_cloud_storage-1.0.5.dist-info/WHEEL
django_cloud_storage-1.0.5.dist-info/top_level.txt
django_cloud_storage-1.0.5.dist-info/RECORD
